mux2.v
module mux2(out, select, in0, in1, in2, in3);

	parameter WORD_SIZE = 16;
	
	output reg [WORD_SIZE-1:0] out;
	input [WORD_SIZE-1:0] in0, in1, in2, in3;
	input [1:0] select;
	
	always@* begin
		case(select)
			2'b00: out = in0;
			2'b01: out = in1;
			2'b10: out = in2;
			2'b11: out = in3;
		endcase
	end
endmodule

ir_decode.v
module ir_decode(instruction_reg, reg_addr2, reg_addr1, reg_addr_in,
					  imm1, imm2, imm3, alu_op, opcode);
	
	parameter WORD_SIZE = 16, REG_ADDR_SIZE = 3, ALU_OP_SIZE = 3;
	
	input [WORD_SIZE-1:0] instruction_reg;
	output [REG_ADDR_SIZE-1:0] reg_addr1, reg_addr2, reg_addr_in;
	output [10:0] imm1;
	output [7:0] imm2;
	output [4:0] imm3;
	output [ALU_OP_SIZE-1:0] alu_op;
	output [4:0] opcode;
	
	wire [REG_ADDR_SIZE-1:0] rc, rb, ra;
	assign ra = instruction_reg[2:0];
	assign rb = instruction_reg[5:3];
	assign rc = instruction_reg[8:6];
	assign imm1 = instruction_reg[10:0];
	assign imm2 = instruction_reg[10:3];
	assign imm3 = instruction_reg[10:6];
	assign opcode = instruction_reg[15:11];
	assign alu_op = opcode[2:0];
	
//	Link register addr
	parameter lr = 3'b111;
	
	parameter br_op = 5'b11111, store_op = 5'b11101,
				 store_r_op = 5'b11001, bl_op = 5'b10100;
	
	assign reg_addr1 = (opcode == br_op || opcode == store_op) ? ra : rb;
	assign reg_addr2 = (opcode == store_r_op) ? ra : rc;
	assign reg_addr_in = (opcode == bl_op) ? lr : ra;
	
endmodule

ALU.v
module ALU(out, flags, op, in_a, in_b);

	parameter WORD_SIZE = 16, OP_SIZE = 3;
	
	output reg[WORD_SIZE-1:0] out;
	output[WORD_SIZE-1:0] flags;
	input[OP_SIZE-1:0] op;
	input[WORD_SIZE-1:0] in_a;
	input[WORD_SIZE-1:0] in_b;
	
	always@(op,in_a,in_b) begin
		case(op)
			1'b0: out = in_a + in_b;
			1'b1: out = in_a - in_b;
			2'b10: out = ~in_a;
			2'b11: out = in_a & in_b;
			3'b100: out = in_a | in_b;
			3'b101: out = in_a ^ in_b;
			3'b110: out = in_a * in_b;
			3'b111: out = in_a / in_b;
		endcase
	end
endmodule

register_file.v
module register_file(reg_buff1, reg_buff2, write, addr1, addr2, addr_in,
							data_in, clk, write_buff1, write_buff2);
	
	parameter WORD_SIZE = 16, REG_NUM = 8;
	
	output reg [WORD_SIZE-1:0] reg_buff1,reg_buff2;
	input write, clk, write_buff1, write_buff2;
	input [2:0] addr1, addr2, addr_in;
	input [WORD_SIZE-1:0] data_in;
	
	reg [WORD_SIZE-1:0] reg_file[REG_NUM:0];
	
	always@(posedge clk) begin
		if(write_buff1)
			reg_buff1 = reg_file[addr1];
		if(write_buff2)
			reg_buff2 = reg_file[addr2];
	end
	
	always@(posedge clk) begin
		if(write) reg_file[addr_in] = data_in;
	end
	
endmodule

datapath.v
module datapath(clk, ALU_in2_mux, mem_out_mux, PC_mux, memory_addr_mux, data_in_mux,
					 reg_buff1_write, reg_buff2_write, status_reg_write, ALU_out_write,
					 reg_write, PC_write, IR_write,
					 memory_in, memory_addr, memory_out,
					 opcode, status_reg);
	
	parameter WORD_SIZE = 16, ALU_OP_SIZE = 3, REG_ADDR_SIZE = 3;
	
// Clock
	input clk;
	
//	Mux select
	input ALU_in2_mux, mem_out_mux;
	input [1:0] PC_mux, memory_addr_mux, data_in_mux;
	
//	Register write
	input reg_buff1_write, reg_buff2_write, status_reg_write, ALU_out_write;
	input reg_write, PC_write, IR_write;
	
//	Memory input/output/addr
	input [WORD_SIZE-1:0] memory_in;
	output [WORD_SIZE-1:0] memory_addr, memory_out;
	
//	Control unit data
	output [4:0] opcode;
	output reg [WORD_SIZE-1:0] status_reg;
	
//	Registers
	reg [WORD_SIZE-1:0] ALU_out_buff, PC, inst_reg;
	
// Wires
	wire [WORD_SIZE-1:0] ALU_out, ALU_flags, ALU_in2, PC_in_wire;
	wire [WORD_SIZE-1:0] reg_buff1, reg_buff2, data_in;
	wire [REG_ADDR_SIZE-1:0] reg_addr1, reg_addr2, reg_addr_in;
	wire [ALU_OP_SIZE-1:0] ALU_op;
	wire [10:0] imm1;
	wire [7:0] imm2;
	wire [4:0] imm3;

//	Register file and mux
	mux2 reg_file_mux(data_in, data_in_mux, ALU_out_buff, memory_in, imm2, PC);
	register_file registers(reg_buff1, reg_buff2, reg_write, reg_addr1, reg_addr2,
									reg_addr_in, data_in, clk, reg_buff1_write, reg_buff2_write);
	
//	ALU, input mux and buffers
	ALU alu(ALU_out, ALU_flags, ALU_op, reg_buff1, ALU_in2);
	
	assign ALU_in2 = ALU_in2_mux ? reg_buff2 : imm3;
	
	always@(posedge clk) if(ALU_out_write) ALU_out_buff <= ALU_out;
	always@(posedge clk) if(status_reg_write) status_reg <= ALU_flags;
	
//	IR input and decoder
	ir_decode ir_decode(inst_reg, reg_addr2, reg_addr1, reg_addr_in,
				 imm1, imm2, imm3, ALU_op, opcode);
	
	always@(posedge clk) if(IR_write) inst_reg <= memory_in;
	
//	PC mux and input
	mux2 PC_mux2(PC_in_wire, PC_mux, PC+1, imm1, reg_buff1, 0);
	
	always@(posedge clk) if(PC_write) PC <= PC_in_wire;
	
//	Memory addr and output mux
	mux2 Memory_mux2(memory_addr, memory_addr_mux, PC, reg_buff1, imm2, ALU_out_buff);
	assign memory_out = (mem_out_mux) ? reg_buff1 : reg_buff2;
	
	initial begin
		PC = 4'b1001;
	end
	
endmodule

control_unit.v
module control_unit(clk, ALU_in2_mux, mem_out_mux, PC_mux, memory_addr_mux, data_in_mux,
						  reg_buff1_write, reg_buff2_write, status_reg_write, ALU_out_write,
						  reg_write, PC_write, IR_write, memory_write, opcode, status_reg);
	
	parameter WORD_SIZE = 16, ALU_OP_SIZE = 3, REG_ADDR_SIZE = 3;
	
// Inputs
	input clk;
	input [4:0] opcode;
	input [WORD_SIZE-1:0] status_reg;
//	Mux select
	output reg ALU_in2_mux, mem_out_mux;
	output reg [1:0] PC_mux, memory_addr_mux, data_in_mux;
//	Write signals
	output reg reg_buff1_write, reg_buff2_write, status_reg_write, ALU_out_write;
	output reg reg_write, PC_write, IR_write, memory_write;
	
	parameter fetch = 0, decode = 1, execute = 2;
	reg [1:0] cycle;
	
	always @(cycle) begin
		disable_write_signals();
		case(cycle)
			fetch: begin
				memory_addr_mux = 0;
				IR_write = 1;
			end
			decode: begin
			end
			execute: begin
			end
		endcase
	end
	
	always @(posedge clk) begin
		case(cycle)
			fetch: cycle <= decode;
			decode: cycle <= execute;
			execute: cycle <= fetch;
		endcase
	end
	
	initial begin
		disable_write_signals();
		zero_muxes();
		cycle = fetch;
	end
	
	task disable_write_signals;
		{reg_buff1_write, reg_buff2_write, status_reg_write, ALU_out_write, 
			reg_write, PC_write, IR_write, memory_write} = 0;
	endtask
	
	task zero_muxes;
		{ALU_in2_mux, mem_out_mux, PC_mux, memory_addr_mux, data_in_mux} = 0;
	endtask
	
endmodule

CPU.v
module CPU(clk, memory_in, memory_addr, memory_out, memory_write);
	parameter WORD_SIZE = 16, ALU_OP_SIZE = 3, REG_ADDR_SIZE = 3;

//	Clock
	input clk;
//	Memory input/output/addr/flag
	input [WORD_SIZE-1:0] memory_in;
	output [WORD_SIZE-1:0] memory_addr, memory_out;
	output memory_write;

//	Mux select
	wire ALU_in2_mux, mem_out_mux;
	wire [1:0] PC_mux, memory_addr_mux, data_in_mux;
//	Register write
	wire reg_buff1_write, reg_buff2_write, status_reg_write, ALU_out_write;
	wire reg_write, PC_write, IR_write;
//	Control unit data
	wire [4:0] opcode;
	wire [WORD_SIZE-1:0] status_reg;

	control_unit control_unit(clk, ALU_in2_mux, mem_out_mux, PC_mux, memory_addr_mux, data_in_mux,
					 reg_buff1_write, reg_buff2_write, status_reg_write, ALU_out_write,
					 reg_write, PC_write, IR_write, memory_write, opcode, status_reg);
	
	datapath datapath(clk, ALU_in2_mux, mem_out_mux, PC_mux, memory_addr_mux, data_in_mux,
				reg_buff1_write, reg_buff2_write, status_reg_write, ALU_out_write,
				reg_write, PC_write, IR_write,
				memory_in, memory_addr, memory_out,
				opcode, status_reg);
	
endmodule

tests/full_cpu_test.v
module full_cpu_test;
	reg clk;
	reg [15:0] memory_in;
	wire [15:0] memory_out, memory_addr;
	wire memory_write;
	
	CPU cpu(clk, memory_in, memory_addr, memory_out, memory_write);
	
	initial begin
		$dumpfile("dump_full_cpu.vcd");
		$dumpvars;
		clk = 0;
		memory_in = 5'b10110;
		#40 memory_in = 16'b1101001011100011;
		
		#300 $finish;
	end

	always #10 clk = ~clk;
endmodule

tests/dump_full_cpu.vcd
$date
	Thu May 17 01:06:12 2018
$end
$version
	Icarus Verilog
$end
$timescale
	1s
$end
$scope module full_cpu_test $end
$var wire 16 ! memory_addr [15:0] $end
$var wire 16 " memory_out [15:0] $end
$var wire 1 # memory_write $end
$var reg 1 $ clk $end
$var reg 16 % memory_in [15:0] $end
$scope module cpu $end
$var wire 1 & ALU_in2_mux $end
$var wire 1 ' ALU_out_write $end
$var wire 1 ( IR_write $end
$var wire 2 ) PC_mux [1:0] $end
$var wire 1 * PC_write $end
$var wire 1 + clk $end
$var wire 2 , data_in_mux [1:0] $end
$var wire 1 - mem_out_mux $end
$var wire 16 . memory_addr [15:0] $end
$var wire 2 / memory_addr_mux [1:0] $end
$var wire 16 0 memory_in [15:0] $end
$var wire 16 1 memory_out [15:0] $end
$var wire 1 # memory_write $end
$var wire 5 2 opcode [4:0] $end
$var wire 1 3 reg_buff1_write $end
$var wire 1 4 reg_buff2_write $end
$var wire 1 5 reg_write $end
$var wire 16 6 status_reg [15:0] $end
$var wire 1 7 status_reg_write $end
$scope module control_unit $end
$var wire 1 + clk $end
$var wire 5 8 opcode [4:0] $end
$var wire 16 9 status_reg [15:0] $end
$var reg 1 : ALU_in2_mux $end
$var reg 1 ; ALU_out_write $end
$var reg 1 < IR_write $end
$var reg 2 = PC_mux [1:0] $end
$var reg 1 > PC_write $end
$var reg 2 ? cycle [1:0] $end
$var reg 2 @ data_in_mux [1:0] $end
$var reg 1 A mem_out_mux $end
$var reg 2 B memory_addr_mux [1:0] $end
$var reg 1 C memory_write $end
$var reg 1 D reg_buff1_write $end
$var reg 1 E reg_buff2_write $end
$var reg 1 F reg_write $end
$var reg 1 G status_reg_write $end
$scope task disable_write_signals $end
$upscope $end
$scope task zero_muxes $end
$upscope $end
$upscope $end
$scope module datapath $end
$var wire 16 H ALU_flags [15:0] $end
$var wire 16 I ALU_in2 [15:0] $end
$var wire 1 & ALU_in2_mux $end
$var wire 3 J ALU_op [2:0] $end
$var wire 16 K ALU_out [15:0] $end
$var wire 1 ' ALU_out_write $end
$var wire 1 ( IR_write $end
$var wire 16 L PC_in_wire [15:0] $end
$var wire 2 M PC_mux [1:0] $end
$var wire 1 * PC_write $end
$var wire 1 + clk $end
$var wire 16 N data_in [15:0] $end
$var wire 2 O data_in_mux [1:0] $end
$var wire 11 P imm1 [10:0] $end
$var wire 8 Q imm2 [7:0] $end
$var wire 5 R imm3 [4:0] $end
$var wire 1 - mem_out_mux $end
$var wire 16 S memory_addr [15:0] $end
$var wire 2 T memory_addr_mux [1:0] $end
$var wire 16 U memory_in [15:0] $end
$var wire 16 V memory_out [15:0] $end
$var wire 5 W opcode [4:0] $end
$var wire 3 X reg_addr1 [2:0] $end
$var wire 3 Y reg_addr2 [2:0] $end
$var wire 3 Z reg_addr_in [2:0] $end
$var wire 16 [ reg_buff1 [15:0] $end
$var wire 1 3 reg_buff1_write $end
$var wire 16 \ reg_buff2 [15:0] $end
$var wire 1 4 reg_buff2_write $end
$var wire 1 5 reg_write $end
$var wire 1 7 status_reg_write $end
$var reg 16 ] ALU_out_buff [15:0] $end
$var reg 16 ^ PC [15:0] $end
$var reg 16 _ inst_reg [15:0] $end
$var reg 16 ` status_reg [15:0] $end
$scope module reg_file_mux $end
$var wire 16 a in0 [15:0] $end
$var wire 16 b in1 [15:0] $end
$var wire 16 c in2 [15:0] $end
$var wire 16 d in3 [15:0] $end
$var wire 2 e select [1:0] $end
$var reg 16 f out [15:0] $end
$upscope $end
$scope module registers $end
$var wire 3 g addr1 [2:0] $end
$var wire 3 h addr2 [2:0] $end
$var wire 3 i addr_in [2:0] $end
$var wire 1 + clk $end
$var wire 16 j data_in [15:0] $end
$var wire 1 5 write $end
$var wire 1 3 write_buff1 $end
$var wire 1 4 write_buff2 $end
$var reg 16 k reg_buff1 [15:0] $end
$var reg 16 l reg_buff2 [15:0] $end
$upscope $end
$scope module alu $end
$var wire 16 m flags [15:0] $end
$var wire 16 n in_a [15:0] $end
$var wire 16 o in_b [15:0] $end
$var wire 3 p op [2:0] $end
$var reg 16 q out [15:0] $end
$upscope $end
$scope module ir_decode $end
$var wire 3 r alu_op [2:0] $end
$var wire 11 s imm1 [10:0] $end
$var wire 8 t imm2 [7:0] $end
$var wire 5 u imm3 [4:0] $end
$var wire 16 v instruction_reg [15:0] $end
$var wire 5 w opcode [4:0] $end
$var wire 3 x ra [2:0] $end
$var wire 3 y rb [2:0] $end
$var wire 3 z rc [2:0] $end
$var wire 3 { reg_addr1 [2:0] $end
$var wire 3 | reg_addr2 [2:0] $end
$var wire 3 } reg_addr_in [2:0] $end
$upscope $end
$scope module PC_mux2 $end
$var wire 16 ~ in0 [15:0] $end
$var wire 16 !" in1 [15:0] $end
$var wire 16 "" in2 [15:0] $end
$var wire 16 #" in3 [15:0] $end
$var wire 2 $" select [1:0] $end
$var reg 16 %" out [15:0] $end
$upscope $end
$scope module Memory_mux2 $end
$var wire 16 &" in0 [15:0] $end
$var wire 16 '" in1 [15:0] $end
$var wire 16 (" in2 [15:0] $end
$var wire 16 )" in3 [15:0] $end
$var wire 2 *" select [1:0] $end
$var reg 16 +" out [15:0] $end
$upscope $end
$upscope $end
$upscope $end
$upscope $end
$enddefinitions $end
#0
$dumpvars
b1001 +"
b0 *"
bx )"
b0xxxxxxxx ("
bx '"
b1001 &"
b1010 %"
b0 $"
b0 #"
bx ""
b0xxxxxxxxxxx !"
b1010 ~
bx }
bx |
bx {
bx z
bx y
bx x
bx w
bx v
bx u
bx t
bx s
bx r
bx q
bx p
b0xxxxx o
bx n
bz m
bx l
bx k
bx j
bx i
bx h
bx g
bx f
b0 e
b1001 d
b0xxxxxxxx c
b10110 b
bx a
bx `
bx _
b1001 ^
bx ]
bx \
bx [
bx Z
bx Y
bx X
bx W
bx V
b10110 U
b0 T
b1001 S
bx R
bx Q
bx P
b0 O
bx N
b0 M
b1010 L
bx K
bx J
b0xxxxx I
bz H
0G
0F
0E
0D
0C
b0 B
0A
b0 @
b0 ?
0>
b0 =
1<
0;
0:
bx 9
bx 8
07
bx 6
05
04
03
bx 2
bx 1
b10110 0
b0 /
b1001 .
0-
b0 ,
0+
0*
b0 )
1(
0'
0&
b10110 %
0$
0#
bx "
b1001 !
$end
#10
b10 X
b10 g
b10 {
b0 I
b0 o
b0 J
b0 p
b0 r
b0 Y
b0 h
b0 |
b110 Z
b110 i
b110 }
0<
0(
b110 x
b10 y
b0 z
b10110 !"
b10110 P
b10110 s
b10 ("
b10 c
b10 Q
b10 t
b0 R
b0 u
b0 2
b0 8
b0 W
b0 w
b1 ?
b10110 _
b10110 v
1$
1+
#20
0$
0+
#30
b10 ?
1$
1+
#40
0$
0+
b1101001011100011 %
b1101001011100011 0
b1101001011100011 U
b1101001011100011 b
#50
1<
1(
b0 ?
1$
1+
#60
0$
0+
#70
b11 Z
b11 i
b11 }
b100 X
b100 g
b100 {
b11 Y
b11 h
b11 |
b1011 I
b1011 o
b10 J
b10 p
b10 r
b11 x
b100 y
b11 z
b1011100011 !"
b1011100011 P
b1011100011 s
b1011100 ("
b1011100 c
b1011100 Q
b1011100 t
b1011 R
b1011 u
b11010 2
b11010 8
b11010 W
b11010 w
0<
0(
b1101001011100011 _
b1101001011100011 v
b1 ?
1$
1+
#80
0$
0+
#90
b10 ?
1$
1+
#100
0$
0+
#110
1<
1(
b0 ?
1$
1+
#120
0$
0+
#130
0<
0(
b1 ?
1$
1+
#140
0$
0+
#150
b10 ?
1$
1+
#160
0$
0+
#170
1<
1(
b0 ?
1$
1+
#180
0$
0+
#190
0<
0(
b1 ?
1$
1+
#200
0$
0+
#210
b10 ?
1$
1+
#220
0$
0+
#230
1<
1(
b0 ?
1$
1+
#240
0$
0+
#250
0<
0(
b1 ?
1$
1+
#260
0$
0+
#270
b10 ?
1$
1+
#280
0$
0+
#290
1<
1(
b0 ?
1$
1+
#300
0$
0+
#310
0<
0(
b1 ?
1$
1+
#320
0$
0+
#330
b10 ?
1$
1+
